LICENSE.txt
README.md
pyproject.toml
setup.cfg
setup.py
meteolib/__init__.py
meteolib/_utils.py
meteolib/_version.py
meteolib/charts.py
meteolib/constants.py
meteolib/evapo.py
meteolib/humidity.py
meteolib/pressure.py
meteolib/radiation.py
meteolib/standard.py
meteolib/temperature.py
meteolib/thermodyn.py
meteolib/wind.py
meteolib.egg-info/PKG-INFO
meteolib.egg-info/SOURCES.txt
meteolib.egg-info/dependency_links.txt
meteolib.egg-info/requires.txt
meteolib.egg-info/top_level.txt
tests/test_evapo.py
tests/test_humidity.py
tests/test_radiation.py
tests/test_standard.py
tests/test_temperature.py
tests/test_thermodyn.py
tests/test_utils.py
tests/test_wind.py