Metadata-Version: 2.4
Name: meteolib
Version: 0.16.21
Summary: Python standard functions for meteorology.
Home-page: 
Author: Clemens Drüe
Author-email: druee@uni-trier.de
License: EUPL-1.2
Keywords: meteorology
License-File: LICENSE.txt
Requires-Dist: numpy
Requires-Dist: pandas
Requires-Dist: pytz
Dynamic: author
Dynamic: author-email
Dynamic: keywords
Dynamic: license
Dynamic: license-file
Dynamic: requires-dist
Dynamic: summary
